swarm/environment/__init__.py
swarm/environment/agents/__init__.py
swarm/environment/agents/adversarial_agent.py
swarm/environment/agents/agent_registry.py
swarm/environment/agents/cot.py
swarm/environment/agents/crosswords/brute_force_opt.py
swarm/environment/agents/crosswords/reflection.py
swarm/environment/agents/crosswords/tot.py
swarm/environment/agents/gaia/normal_io.py
swarm/environment/agents/gaia/tool_io.py
swarm/environment/agents/gaia/tool_tot.py
swarm/environment/agents/gaia/web_io.py
swarm/environment/agents/humaneval/code_io.py
swarm/environment/agents/humaneval/code_react.py
swarm/environment/agents/io.py
swarm/environment/agents/tot.py
swarm/environment/domain/crosswords/env.py
swarm/environment/domain/crosswords/evaluator.py
swarm/environment/domain/crosswords/parser.py
swarm/environment/domain/gaia/__init__.py
swarm/environment/domain/gaia/evaluation/README.md
swarm/environment/domain/gaia/evaluation/app.py
swarm/environment/domain/gaia/evaluation/content.py
swarm/environment/domain/gaia/evaluation/requirements.txt
swarm/environment/domain/gaia/evaluation/scorer.py
swarm/environment/operations/__init__.py
swarm/environment/operations/adversarial_answer.py
swarm/environment/operations/combine_answer.py
swarm/environment/operations/cot_step.py
swarm/environment/operations/crosswords/__init__.py
swarm/environment/operations/crosswords/branching_step.py
swarm/environment/operations/crosswords/brute_force_step.py
swarm/environment/operations/crosswords/crosswords_operation.py
swarm/environment/operations/crosswords/greedy_steps.py
swarm/environment/operations/crosswords/reflection.py
swarm/environment/operations/crosswords/return_all.py
swarm/environment/operations/direct_answer.py
swarm/environment/operations/file_analyse.py
swarm/environment/operations/final_decision.py
swarm/environment/operations/generate_query.py
swarm/environment/operations/humaneval/code_writing.py
swarm/environment/operations/humaneval/unitest_generation.py
gptswarm-0.1.0.dist-info/LICENSE
gptswarm-0.1.0.dist-info/METADATA
gptswarm-0.1.0.dist-info/WHEEL
gptswarm-0.1.0.dist-info/RECORD
