Metadata-Version: 2.1
Name: gptswarm
Version: 0.1.0
Summary: GPTSwarm: Language Agents as Optimizable Graphs
Author: Mingchen Zhuge
Author-email: mczhuge@gmail.com
Requires-Python: >=3.10,<4.0
Classifier: Programming Language :: Python :: 3
Classifier: Programming Language :: Python :: 3.10
Classifier: Programming Language :: Python :: 3.11
Classifier: Programming Language :: Python :: 3.12
Requires-Dist: aiohttp (>=3.9.0,<4.0.0)
Requires-Dist: apscheduler (>=3.10.4,<4.0.0)
Requires-Dist: arxiv (>=2.0.0,<3.0.0)
Requires-Dist: astunparse (>=1.6.3,<2.0.0)
Requires-Dist: async-timeout (>=4.0.3,<5.0.0)
Requires-Dist: beautifulsoup4 (>=4.12.2,<5.0.0)
Requires-Dist: charset-normalizer (>=3.3.2,<4.0.0)
Requires-Dist: class-registry (>=2.1.2,<3.0.0)
Requires-Dist: docx (>=0.2.4,<0.3.0)
Requires-Dist: fastapi (==0.109.2)
Requires-Dist: func-timeout (>=4.3.5,<5.0.0)
Requires-Dist: google-api-python-client (>=2.111.0,<3.0.0)
Requires-Dist: gradio (>=4.11.0,<5.0.0)
Requires-Dist: httpx (>=0.25.2,<0.26.0)
Requires-Dist: jsonlines (>=4.0.0,<5.0.0)
Requires-Dist: loguru (==0.7.2)
Requires-Dist: markdown (>=3.5.1,<4.0.0)
Requires-Dist: networkx (==3.2.1)
Requires-Dist: openai (>=1.6.0,<2.0.0)
Requires-Dist: opencv-python (>=4.8.1.78,<5.0.0.0)
Requires-Dist: openpyxl (>=3.1.2,<4.0.0)
Requires-Dist: pandas (>=1.5.3,<2.0.0)
Requires-Dist: pydantic (>=2.5.3,<3.0.0)
Requires-Dist: pylatexenc (>=2.10,<3.0)
Requires-Dist: pypdf2 (>=3.0.1,<4.0.0)
Requires-Dist: python-docx (>=1.1.0,<2.0.0)
Requires-Dist: python-dotenv (==1.0.0)
Requires-Dist: python-pptx (==0.6.23)
Requires-Dist: pytube (==15.0.0)
Requires-Dist: pyvis (==0.3.2)
Requires-Dist: pyyaml (==6.0.1)
Requires-Dist: regex (==2023.10.3)
Requires-Dist: requests (>=2.31.0,<3.0.0)
Requires-Dist: scipy (>=1.12.0,<2.0.0)
Requires-Dist: seaborn (>=0.13.1,<0.14.0)
Requires-Dist: sentence-transformers (==2.2.2)
Requires-Dist: shortuuid (==1.0.11)
Requires-Dist: tenacity (>=8.2.3,<9.0.0)
Requires-Dist: termcolor (>=2.4.0,<3.0.0)
Requires-Dist: torch (>=2.1.0,<3.0.0)
Requires-Dist: tqdm (>=4.66.1,<5.0.0)
Requires-Dist: transformers (>=4.36.2,<5.0.0)
Requires-Dist: wikipedia (>=1.4.0,<2.0.0)
